hashwire/__init__.py
hashwire/hash.py
hashwire-0.0.2.dist-info/LICENSE
hashwire-0.0.2.dist-info/METADATA
hashwire-0.0.2.dist-info/WHEEL
hashwire-0.0.2.dist-info/top_level.txt
hashwire-0.0.2.dist-info/RECORD
