Metadata-Version: 2.1
Name: hashwire
Version: 0.0.2
Summary: Hashwire creates a optimized hash multichain commitment
Author-email: Hugo Labraaten <hugokinner@gmail.com>
License: MIT License
Project-URL: repository, https://github.com/Hugloss/hashWire
Classifier: Development Status :: 4 - Beta
Classifier: License :: OSI Approved :: MIT License
Classifier: Programming Language :: Python :: 3
Classifier: Operating System :: OS Independent
License-File: LICENSE
